openweatherclass/__init__.py
openweatherclass/condition_codes.py
openweatherclass/functions.py
openweatherclass/geodataclass.py
openweatherclass/historydataclass.py
openweatherclass/weatherclass.py
openweatherclass/weatherdataclass.py
openweatherclass-0.5.1.dist-info/WHEEL
openweatherclass-0.5.1.dist-info/METADATA
openweatherclass-0.5.1.dist-info/LICENSE
openweatherclass-0.5.1.dist-info/RECORD
